tikotmusicaly.py
tikotmusicaly-1.0.0.dist-info/WHEEL
tikotmusicaly-1.0.0.dist-info/METADATA
tikotmusicaly-1.0.0.dist-info/RECORD
