Metadata-Version: 2.1
Name: tikotmusicaly
Version: 1.0.0
Summary: View your tracks uploaded on TikOt Musica.ly!
License: TikOt Producy
Author: TikOt Python Library
Author-email: tikotstudio@yandex.ru
Requires-Python: >=3.7,<4.0
Classifier: License :: Other/Proprietary License
Classifier: Programming Language :: Python :: 3
Classifier: Programming Language :: Python :: 3.7
Classifier: Programming Language :: Python :: 3.8
Classifier: Programming Language :: Python :: 3.9
